flexnote/__init__.py
flexnote/hello.py
flexnote-0.1.1.dist-info/METADATA
flexnote-0.1.1.dist-info/WHEEL
flexnote-0.1.1.dist-info/entry_points.txt
flexnote-0.1.1.dist-info/RECORD
